jquant/__init__.py
jquant/exchange.py
jquant/exchange_test.py
jquant/platform_pb2.py
jquant/platform_pb2.pyi
jquant/platform_pb2_grpc.py
jquant-0.1.1.dist-info/METADATA
jquant-0.1.1.dist-info/WHEEL
jquant-0.1.1.dist-info/top_level.txt
jquant-0.1.1.dist-info/RECORD
