Metadata-Version: 2.1
Name: jquant
Version: 0.1.1
Summary: jquant python client
Author-email: enoch <lanxenet@gmail.com>
License: MIT
Requires-Python: >=3.11
Requires-Dist: grpcio >=1.64.0
Requires-Dist: protobuf >=3.20.3
